eda/__init__.py
eda/commuter_aggregates.py
eda/mobility_summary.py
mobility/__init__.py
mobility/eda/__init__.py
mobility/eda/commuter_aggregates.py
mobility/eda/mobility_summary.py
mobility/odm/__init__.py
mobility/odm/main.py
mobility/odm/odm.py
mobility/odm/utils.py
mobility/stm/__init__.py
mobility/stm/aggregation.py
mobility/stm/main.py
mobility/stm/stm.py
odm/__init__.py
odm/main.py
odm/odm.py
odm/utils.py
stm/__init__.py
stm/aggregation.py
stm/main.py
stm/stm.py
pymobility-0.0.3.dist-info/LICENSE
pymobility-0.0.3.dist-info/METADATA
pymobility-0.0.3.dist-info/WHEEL
pymobility-0.0.3.dist-info/top_level.txt
pymobility-0.0.3.dist-info/RECORD
