Metadata-Version: 2.1
Name: pymobility
Version: 0.0.3
Summary: Python mobility library
Home-page: https://github.com/datapartnership/covid19-migration-south-asia
Author: Suraj Regmi
Author-email: regmi125@gmail.com
License: UNKNOWN
Platform: UNKNOWN
Classifier: Programming Language :: Python :: 3
Classifier: License :: OSI Approved :: MIT License
Classifier: Operating System :: OS Independent
Requires-Python: >=3.6
